prtg_cli/__init__.py
prtg_cli/cli.py
prtg_cli/commands/__init__.py
prtg_cli/commands/duplicate.py
prtg_cli/commands/get.py
prtg_cli/commands/manager.py
prtg_cli/commands/object.py
prtg_cli/core/__init__.py
prtg_cli/core/config.py
prtg_cli/core/constants.py
prtg_cli/core/converters.py
prtg_cli-0.2.1.dist-info/entry_points.txt
prtg_cli-0.2.1.dist-info/LICENSE
prtg_cli-0.2.1.dist-info/WHEEL
prtg_cli-0.2.1.dist-info/METADATA
prtg_cli-0.2.1.dist-info/RECORD
