Metadata-Version: 2.1
Name: prtg-cli
Version: 0.2.1
Summary: CLI for PRTG Network Monitor
Home-page: https://github.com/f9n/prtg-cli
License: GPL-3.0
Author: Fatih Sarhan
Author-email: f9n@protonmail.com
Requires-Python: >=3.7,<4.0
Classifier: License :: OSI Approved :: GNU General Public License v3 (GPLv3)
Classifier: Programming Language :: Python :: 3
Classifier: Programming Language :: Python :: 3.7
Requires-Dist: click (>=7.0,<8.0)
Requires-Dist: jsonschema (>=3.1,<4.0)
Requires-Dist: pyyaml (>=5.1,<6.0)
Requires-Dist: requests (>=2.22,<3.0)
Requires-Dist: xmltodict (>=0.12.0,<0.13.0)
Project-URL: Repository, https://github.com/f9n/prtg-cli
